[
  { "id": "g1-seifu",       "grade": "中1", "title": "正負の数",       "subtitle": "数の向きと符号を、ゆっくり確認する", "status": "available", "order": 1 },
  { "id": "g1-mojishiki",   "grade": "中1", "title": "文字式",          "subtitle": "文字の書き方とまとめ方に慣れる", "status": "available", "order": 2 },
  { "id": "g1-linear-eq",   "grade": "中1", "title": "一次方程式",      "subtitle": "「次に何をする？」で解けるようになる", "status": "available", "order": 3 },
  { "id": "g1-hirei",       "grade": "中1", "title": "比例・反比例",    "subtitle": "表と式で、変わり方をつかむ", "status": "available", "order": 4 },
  { "id": "g1-zukei",       "grade": "中1", "title": "図形",            "subtitle": "図を見ながら角度の考え方をつかむ", "status": "available", "order": 5 },

  { "id": "g2-shiki",       "grade": "中2", "title": "式の計算",        "subtitle": "単項式・多項式の計算を入試の土台にする", "status": "available", "order": 1 },
  { "id": "g2-renritsu",    "grade": "中2", "title": "連立方程式",      "subtitle": "2つの条件を式にして、答えまで進む", "status": "available", "order": 2 },
  { "id": "g2-linear-fn",   "grade": "中2", "title": "一次関数",        "subtitle": "直線の式とグラフをつなげる", "status": "available", "order": 3 },
  { "id": "g2-shomei",      "grade": "中2", "title": "図形の証明",      "subtitle": null, "status": "comingSoon", "order": 4 },
  { "id": "g2-kakuritsu",   "grade": "中2", "title": "確率",            "subtitle": "場合の数を整理して、確率を出す", "status": "available", "order": 5 },

  { "id": "g3-tenkai",      "grade": "中3", "title": "展開・因数分解",  "subtitle": "公式を使って、式を広げる・戻す", "status": "available", "order": 1 },
  { "id": "g3-heihokon",    "grade": "中3", "title": "平方根",          "subtitle": "ルートの計算と大小を整理する", "status": "available", "order": 2 },
  { "id": "g3-quad-eq",     "grade": "中3", "title": "二次方程式",      "subtitle": "因数分解・平方根・解の公式で解く", "status": "available", "order": 3 },
  { "id": "g3-quad-fn",     "grade": "中3", "title": "二次関数",        "subtitle": "y = ax^2 の形とグラフをつなげる", "status": "available", "order": 4 },
  { "id": "g3-soji",        "grade": "中3", "title": "相似",            "subtitle": null, "status": "comingSoon", "order": 5 },
  { "id": "g3-sanpei",      "grade": "中3", "title": "三平方の定理",    "subtitle": null, "status": "comingSoon", "order": 6 }
]
